README
setup.cfg
setup.py
stearns_cliff/__init__.py
stearns_cliff/cli.py
stearns_cliff/model.py
stearns_cliff/sql.py
stearns_cliff.egg-info/PKG-INFO
stearns_cliff.egg-info/SOURCES.txt
stearns_cliff.egg-info/dependency_links.txt
stearns_cliff.egg-info/entry_points.txt
stearns_cliff.egg-info/requires.txt
stearns_cliff.egg-info/top_level.txt