Metadata-Version: 1.2
Name: stearns-cliff
Version: 0.0.1
Summary: stearns_cliff
Home-page: http://stearns_cliff.readthedocs.io/en/latest/index.html
Author: Stearns Financial Services
Author-email: softwaredevelopment@stearnsbank.com
License: MIT
Download-URL: https://github.com/stearns/stearns_cliff/archive/0.0.1.tar.gz
Platform: UNKNOWN
Classifier: Development Status :: 3 - Alpha
Classifier: Intended Audience :: Developers
Classifier: Topic :: Software Development :: Libraries
Classifier: License :: OSI Approved :: MIT License
Classifier: Programming Language :: Python :: 3.6
Requires-Python: >=3.6
